settings_json/__init__.py
settings_json/models.py
settings_json/utils.py
django_settings_json-1.0.3.dist-info/LICENSE
django_settings_json-1.0.3.dist-info/METADATA
django_settings_json-1.0.3.dist-info/WHEEL
django_settings_json-1.0.3.dist-info/top_level.txt
django_settings_json-1.0.3.dist-info/RECORD
